{"isAddBias":true,"inputs":[{"id":0,"x":0.1,"incoming":[]},{"id":1,"x":0.1,"incoming":[]},{"id":2,"x":0.1,"incoming":[]},{"id":3,"x":0.1,"incoming":[]},{"id":4,"x":0.1,"incoming":[]},{"id":5,"x":0.1,"incoming":[]},{"id":6,"x":0.1,"incoming":[]},{"id":7,"x":0.1,"incoming":[]},{"id":8,"x":0.1,"incoming":[]}],"hidden":[{"id":46,"x":0.29999998,"incoming":[{"fromId":0,"weight":0.3572077,"enabled":true}]},{"id":53,"x":0.29999998,"incoming":[{"fromId":2,"weight":0.15057392,"enabled":true},{"fromId":0,"weight":0.26980123,"enabled":true}]},{"id":57,"x":0.29999998,"incoming":[{"fromId":8,"weight":0.42000496,"enabled":true},{"fromId":0,"weight":0.48215228,"enabled":true}]},{"id":13,"x":0.49999997,"incoming":[{"fromId":1,"weight":0.41095674,"enabled":true},{"fromId":0,"weight":0.13980088,"enabled":true},{"fromId":3,"weight":1.4363405,"enabled":true},{"fromId":2,"weight":-0.45450604,"enabled":false},{"fromId":8,"weight":-0.2823424,"enabled":true},{"fromId":53,"weight":-0.3187647,"enabled":true},{"fromId":57,"weight":-0.53914374,"enabled":true}]},{"id":14,"x":0.49999997,"incoming":[{"fromId":4,"weight":1.2885838,"enabled":true},{"fromId":0,"weight":-0.67245454,"enabled":true},{"fromId":5,"weight":-0.27751306,"enabled":true}]},{"id":17,"x":0.49999997,"incoming":[{"fromId":0,"weight":-0.30631787,"enabled":true},{"fromId":5,"weight":0.3594013,"enabled":true},{"fromId":1,"weight":0.90390176,"enabled":true}]},{"id":19,"x":0.49999997,"incoming":[{"fromId":0,"weight":-0.44208395,"enabled":true},{"fromId":3,"weight":0.19249836,"enabled":true},{"fromId":8,"weight":0.7108554,"enabled":true},{"fromId":57,"weight":2.3393447,"enabled":true}]},{"id":20,"x":0.49999997,"incoming":[{"fromId":3,"weight":0.2670737,"enabled":true},{"fromId":0,"weight":-1.9312459,"enabled":true}]},{"id":21,"x":0.49999997,"incoming":[{"fromId":1,"weight":-1.6797205,"enabled":true},{"fromId":0,"weight":0.5347384,"enabled":true},{"fromId":6,"weight":1.0010859,"enabled":true}]},{"id":25,"x":0.49999997,"incoming":[{"fromId":1,"weight":0.4238364,"enabled":true},{"fromId":0,"weight":-0.24242504,"enabled":true}]},{"id":28,"x":0.49999997,"incoming":[{"fromId":3,"weight":0.40746742,"enabled":true},{"fromId":0,"weight":-1.0502825,"enabled":true},{"fromId":2,"weight":0.23805447,"enabled":true},{"fromId":30,"weight":0.13873519,"enabled":true}]},{"id":29,"x":0.49999997,"incoming":[{"fromId":2,"weight":1.0488129,"enabled":true},{"fromId":0,"weight":-0.035415597,"enabled":true}]},{"id":30,"x":0.49999997,"incoming":[{"fromId":1,"weight":-0.36998653,"enabled":true},{"fromId":0,"weight":-0.35235274,"enabled":true},{"fromId":4,"weight":0.16110572,"enabled":true},{"fromId":5,"weight":1.3644056,"enabled":true},{"fromId":3,"weight":-0.9555894,"enabled":true}]},{"id":33,"x":0.49999997,"incoming":[{"fromId":0,"weight":0.8885046,"enabled":true},{"fromId":3,"weight":-0.033180207,"enabled":true}]},{"id":37,"x":0.49999997,"incoming":[{"fromId":0,"weight":1.1674978,"enabled":true},{"fromId":46,"weight":-1.8355031,"enabled":true}]},{"id":70,"x":0.59999996,"incoming":[{"fromId":19,"weight":-0.27470142,"enabled":true},{"fromId":0,"weight":0.47536933,"enabled":true}]},{"id":97,"x":0.59999996,"incoming":[{"fromId":29,"weight":0.3126397,"enabled":true},{"fromId":0,"weight":-0.22471893,"enabled":true}]},{"id":105,"x":0.59999996,"incoming":[{"fromId":25,"weight":0.13939357,"enabled":true},{"fromId":0,"weight":-0.03312908,"enabled":true}]},{"id":26,"x":0.7,"incoming":[{"fromId":1,"weight":-0.88296574,"enabled":true},{"fromId":0,"weight":0.8124155,"enabled":true},{"fromId":5,"weight":0.5614286,"enabled":true}]},{"id":27,"x":0.7,"incoming":[{"fromId":2,"weight":0.12893344,"enabled":true},{"fromId":0,"weight":0.7919909,"enabled":true},{"fromId":28,"weight":0.4682691,"enabled":true}]},{"id":39,"x":0.7,"incoming":[{"fromId":17,"weight":1.3375556,"enabled":true},{"fromId":0,"weight":-0.3406738,"enabled":true},{"fromId":25,"weight":0.5935898,"enabled":false},{"fromId":105,"weight":0.36754042,"enabled":true},{"fromId":29,"weight":-0.5540129,"enabled":true}]},{"id":42,"x":0.7,"incoming":[{"fromId":19,"weight":-0.39042696,"enabled":false},{"fromId":0,"weight":-1.0069739,"enabled":true},{"fromId":70,"weight":1.3053184,"enabled":true}]},{"id":58,"x":0.7,"incoming":[{"fromId":29,"weight":-0.25660467,"enabled":false},{"fromId":0,"weight":-1.4192123,"enabled":true},{"fromId":97,"weight":-0.1524649,"enabled":true}]},{"id":83,"x":0.9,"incoming":[{"fromId":9,"weight":0.09650499,"enabled":true},{"fromId":0,"weight":1.0104823,"enabled":true},{"fromId":98,"weight":-0.36029035,"enabled":true},{"fromId":3,"weight":1.1480116,"enabled":true},{"fromId":100,"weight":-0.22729659,"enabled":true}]},{"id":98,"x":0.9,"incoming":[{"fromId":9,"weight":0.4466232,"enabled":true},{"fromId":0,"weight":0.47463956,"enabled":true}]},{"id":100,"x":0.9,"incoming":[{"fromId":98,"weight":-0.78125286,"enabled":true},{"fromId":0,"weight":-0.11125254,"enabled":true}]}],"outputs":[{"id":9,"x":0.9,"incoming":[{"fromId":0,"weight":0.6627693,"enabled":true},{"fromId":1,"weight":2.6905866,"enabled":true},{"fromId":2,"weight":-0.6629131,"enabled":true},{"fromId":3,"weight":-0.09076004,"enabled":true},{"fromId":4,"weight":-0.7857453,"enabled":true},{"fromId":13,"weight":0.5505706,"enabled":true},{"fromId":19,"weight":1.5381631,"enabled":true},{"fromId":10,"weight":-0.07708962,"enabled":true},{"fromId":42,"weight":-1.3132749,"enabled":true},{"fromId":9,"weight":-0.81706357,"enabled":true},{"fromId":27,"weight":-0.8874446,"enabled":true},{"fromId":83,"weight":-0.28387892,"enabled":true}]},{"id":10,"x":0.9,"incoming":[{"fromId":0,"weight":-0.43355203,"enabled":false},{"fromId":1,"weight":-0.67189705,"enabled":true},{"fromId":2,"weight":0.19442803,"enabled":true},{"fromId":3,"weight":-0.7451019,"enabled":true},{"fromId":4,"weight":0.25286907,"enabled":true},{"fromId":28,"weight":0.33982122,"enabled":true},{"fromId":13,"weight":-0.6343864,"enabled":true},{"fromId":30,"weight":0.45960742,"enabled":true},{"fromId":37,"weight":0.4779778,"enabled":true},{"fromId":26,"weight":-0.2052392,"enabled":true},{"fromId":29,"weight":-0.7866194,"enabled":true},{"fromId":7,"weight":-0.97669786,"enabled":true},{"fromId":33,"weight":-0.4779184,"enabled":true},{"fromId":58,"weight":0.69611025,"enabled":true}]},{"id":11,"x":0.9,"incoming":[{"fromId":0,"weight":0.9529395,"enabled":true},{"fromId":1,"weight":0.51192176,"enabled":true},{"fromId":2,"weight":-0.47306263,"enabled":true},{"fromId":3,"weight":-0.06921436,"enabled":true},{"fromId":4,"weight":-0.6146976,"enabled":true},{"fromId":25,"weight":0.09490129,"enabled":true},{"fromId":8,"weight":1.4768176,"enabled":true},{"fromId":20,"weight":-0.23854092,"enabled":true},{"fromId":21,"weight":-0.041843295,"enabled":true},{"fromId":7,"weight":0.06432035,"enabled":true}]},{"id":12,"x":0.9,"incoming":[{"fromId":0,"weight":-1.597317,"enabled":true},{"fromId":1,"weight":0.0028961971,"enabled":true},{"fromId":2,"weight":-0.60569644,"enabled":true},{"fromId":3,"weight":0.839476,"enabled":true},{"fromId":4,"weight":0.38954905,"enabled":true},{"fromId":13,"weight":0.1232453,"enabled":true},{"fromId":17,"weight":-0.8602142,"enabled":true},{"fromId":21,"weight":-0.39894664,"enabled":true},{"fromId":28,"weight":-2.3462481,"enabled":true},{"fromId":39,"weight":-0.19532543,"enabled":true},{"fromId":6,"weight":-0.44570062,"enabled":true},{"fromId":14,"weight":-1.3164864,"enabled":true},{"fromId":19,"weight":0.054184556,"enabled":true}]}]}