{"isAddBias":true,"inputs":[{"id":0,"x":0.1,"incoming":[]},{"id":1,"x":0.1,"incoming":[]},{"id":2,"x":0.1,"incoming":[]},{"id":3,"x":0.1,"incoming":[]},{"id":4,"x":0.1,"incoming":[]},{"id":5,"x":0.1,"incoming":[]},{"id":6,"x":0.1,"incoming":[]},{"id":7,"x":0.1,"incoming":[]},{"id":8,"x":0.1,"incoming":[]},{"id":9,"x":0.1,"incoming":[]}],"hidden":[{"id":47,"x":0.29999998,"incoming":[{"fromId":0,"weight":-1.1459819,"enabled":true}]},{"id":54,"x":0.29999998,"incoming":[{"fromId":2,"weight":0.9450079,"enabled":true},{"fromId":0,"weight":-0.5851983,"enabled":true}]},{"id":58,"x":0.29999998,"incoming":[{"fromId":8,"weight":-0.43325678,"enabled":true},{"fromId":0,"weight":-0.49724245,"enabled":true}]},{"id":55,"x":0.39999998,"incoming":[{"fromId":1,"weight":0.7182794,"enabled":true},{"fromId":0,"weight":-1.1102116,"enabled":true}]},{"id":69,"x":0.39999998,"incoming":[{"fromId":5,"weight":-0.01356788,"enabled":true},{"fromId":0,"weight":0.17239377,"enabled":true}]},{"id":14,"x":0.49999997,"incoming":[{"fromId":1,"weight":0.0049529076,"enabled":true},{"fromId":0,"weight":-0.06390926,"enabled":true},{"fromId":3,"weight":0.11312485,"enabled":true},{"fromId":2,"weight":-0.03276494,"enabled":true},{"fromId":8,"weight":0.64910406,"enabled":true},{"fromId":54,"weight":-0.13146824,"enabled":true},{"fromId":58,"weight":-0.7268093,"enabled":true}]},{"id":15,"x":0.49999997,"incoming":[{"fromId":4,"weight":-0.37754485,"enabled":true},{"fromId":0,"weight":-0.18636951,"enabled":true},{"fromId":5,"weight":0.33115947,"enabled":true}]},{"id":18,"x":0.49999997,"incoming":[{"fromId":0,"weight":-1.2176261,"enabled":true},{"fromId":8,"weight":-0.02129671,"enabled":true},{"fromId":1,"weight":-0.41992408,"enabled":true}]},{"id":20,"x":0.49999997,"incoming":[{"fromId":0,"weight":0.076020405,"enabled":true},{"fromId":8,"weight":1.3939526,"enabled":true},{"fromId":58,"weight":0.50311553,"enabled":true}]},{"id":21,"x":0.49999997,"incoming":[{"fromId":3,"weight":1.1352319,"enabled":true},{"fromId":0,"weight":-1.5152719,"enabled":true}]},{"id":22,"x":0.49999997,"incoming":[{"fromId":1,"weight":-1.0368915,"enabled":true},{"fromId":0,"weight":-0.28795898,"enabled":true}]},{"id":26,"x":0.49999997,"incoming":[{"fromId":1,"weight":0.492271,"enabled":true},{"fromId":0,"weight":-0.50912774,"enabled":true},{"fromId":5,"weight":0.45729578,"enabled":true},{"fromId":54,"weight":-0.5316229,"enabled":true}]},{"id":29,"x":0.49999997,"incoming":[{"fromId":3,"weight":0.0125992205,"enabled":true},{"fromId":0,"weight":-0.11987906,"enabled":true},{"fromId":2,"weight":-2.579109,"enabled":true}]},{"id":30,"x":0.49999997,"incoming":[{"fromId":2,"weight":1.6478176,"enabled":true},{"fromId":0,"weight":-0.51160693,"enabled":true},{"fromId":8,"weight":0.76844394,"enabled":true}]},{"id":31,"x":0.49999997,"incoming":[{"fromId":1,"weight":0.295226,"enabled":true},{"fromId":0,"weight":0.5449121,"enabled":true},{"fromId":4,"weight":-0.70331806,"enabled":true},{"fromId":5,"weight":0.35417163,"enabled":true}]},{"id":34,"x":0.49999997,"incoming":[{"fromId":0,"weight":-0.9603125,"enabled":true},{"fromId":3,"weight":-1.1186152,"enabled":true}]},{"id":38,"x":0.49999997,"incoming":[{"fromId":0,"weight":-1.1347885,"enabled":true},{"fromId":47,"weight":-1.0405537,"enabled":true}]},{"id":71,"x":0.59999996,"incoming":[{"fromId":20,"weight":1.2641878,"enabled":true},{"fromId":0,"weight":-0.8860206,"enabled":true}]},{"id":27,"x":0.7,"incoming":[{"fromId":1,"weight":-0.8005906,"enabled":true},{"fromId":0,"weight":0.3621336,"enabled":true},{"fromId":5,"weight":1.3948904,"enabled":true},{"fromId":55,"weight":0.035633966,"enabled":true},{"fromId":69,"weight":0.9132892,"enabled":true}]},{"id":28,"x":0.7,"incoming":[{"fromId":2,"weight":0.5628175,"enabled":true},{"fromId":0,"weight":-0.0739267,"enabled":true},{"fromId":29,"weight":1.3846252,"enabled":true}]},{"id":40,"x":0.7,"incoming":[{"fromId":18,"weight":-0.8805454,"enabled":true},{"fromId":0,"weight":-1.7628754,"enabled":true},{"fromId":2,"weight":-0.7927892,"enabled":true},{"fromId":22,"weight":-1.5679702,"enabled":true}]},{"id":41,"x":0.7,"incoming":[{"fromId":22,"weight":0.39779812,"enabled":true},{"fromId":0,"weight":1.0445895,"enabled":true}]},{"id":43,"x":0.7,"incoming":[{"fromId":20,"weight":2.234132,"enabled":false},{"fromId":0,"weight":-0.87094045,"enabled":true},{"fromId":71,"weight":0.28409111,"enabled":true}]},{"id":59,"x":0.7,"incoming":[{"fromId":30,"weight":0.121469185,"enabled":true},{"fromId":0,"weight":1.0181994,"enabled":true}]},{"id":81,"x":0.7,"incoming":[{"fromId":29,"weight":0.017593384,"enabled":true},{"fromId":0,"weight":-0.71224916,"enabled":true}]},{"id":52,"x":0.79999995,"incoming":[{"fromId":43,"weight":-0.5169852,"enabled":true},{"fromId":0,"weight":-1.763715,"enabled":true},{"fromId":3,"weight":1.4205236,"enabled":true}]},{"id":84,"x":0.9,"incoming":[{"fromId":10,"weight":-0.57378364,"enabled":true},{"fromId":0,"weight":0.32312176,"enabled":true}]}],"outputs":[{"id":10,"x":0.9,"incoming":[{"fromId":0,"weight":-0.3390454,"enabled":true},{"fromId":1,"weight":2.7918704,"enabled":true},{"fromId":2,"weight":-0.07682148,"enabled":false},{"fromId":3,"weight":-0.4578553,"enabled":true},{"fromId":4,"weight":0.5726114,"enabled":true},{"fromId":14,"weight":-0.08978456,"enabled":true},{"fromId":20,"weight":-0.95823795,"enabled":true},{"fromId":11,"weight":0.040766127,"enabled":true},{"fromId":43,"weight":-0.100889,"enabled":true},{"fromId":10,"weight":-0.9233395,"enabled":true},{"fromId":31,"weight":-1.5533291,"enabled":true},{"fromId":52,"weight":0.66102767,"enabled":true},{"fromId":28,"weight":-0.31947294,"enabled":true},{"fromId":84,"weight":-0.3737636,"enabled":true},{"fromId":41,"weight":1.5183848,"enabled":true}]},{"id":11,"x":0.9,"incoming":[{"fromId":0,"weight":-0.6941733,"enabled":true},{"fromId":1,"weight":-2.5013628,"enabled":true},{"fromId":2,"weight":0.90606904,"enabled":true},{"fromId":3,"weight":-1.4086345,"enabled":true},{"fromId":4,"weight":-0.31676763,"enabled":true},{"fromId":29,"weight":-1.368925,"enabled":true},{"fromId":14,"weight":0.7666004,"enabled":true},{"fromId":31,"weight":-0.58058155,"enabled":true},{"fromId":38,"weight":0.31228754,"enabled":true},{"fromId":27,"weight":0.53234875,"enabled":true},{"fromId":30,"weight":1.3800807,"enabled":true},{"fromId":5,"weight":0.019095317,"enabled":true},{"fromId":7,"weight":0.109331995,"enabled":true},{"fromId":34,"weight":-0.8277886,"enabled":true},{"fromId":59,"weight":0.85377693,"enabled":true}]},{"id":12,"x":0.9,"incoming":[{"fromId":0,"weight":0.6140166,"enabled":true},{"fromId":1,"weight":-0.5700724,"enabled":true},{"fromId":2,"weight":-0.62500983,"enabled":true},{"fromId":3,"weight":0.5514211,"enabled":true},{"fromId":4,"weight":-0.18826032,"enabled":true},{"fromId":26,"weight":-1.0966755,"enabled":true},{"fromId":21,"weight":-0.045638695,"enabled":true},{"fromId":31,"weight":1.4272032,"enabled":true},{"fromId":22,"weight":-0.60766715,"enabled":true},{"fromId":7,"weight":-0.94443494,"enabled":true}]},{"id":13,"x":0.9,"incoming":[{"fromId":0,"weight":-0.87920487,"enabled":true},{"fromId":1,"weight":-0.013554012,"enabled":true},{"fromId":2,"weight":-0.9561188,"enabled":true},{"fromId":3,"weight":0.4644325,"enabled":true},{"fromId":4,"weight":0.4583792,"enabled":true},{"fromId":14,"weight":0.18701394,"enabled":true},{"fromId":18,"weight":-1.1281705,"enabled":true},{"fromId":22,"weight":0.10290569,"enabled":true},{"fromId":29,"weight":-0.2850343,"enabled":true},{"fromId":40,"weight":0.15404414,"enabled":true},{"fromId":6,"weight":-0.9799283,"enabled":true},{"fromId":41,"weight":0.16623601,"enabled":true},{"fromId":15,"weight":-0.17172945,"enabled":true},{"fromId":20,"weight":-0.21270126,"enabled":true},{"fromId":81,"weight":-0.12148739,"enabled":true}]}]}