{"isAddBias":true,"inputs":[{"id":0,"x":0.1,"incoming":[]},{"id":1,"x":0.1,"incoming":[]},{"id":2,"x":0.1,"incoming":[]},{"id":3,"x":0.1,"incoming":[]},{"id":4,"x":0.1,"incoming":[]},{"id":5,"x":0.1,"incoming":[]},{"id":6,"x":0.1,"incoming":[]},{"id":7,"x":0.1,"incoming":[]},{"id":8,"x":0.1,"incoming":[]},{"id":9,"x":0.1,"incoming":[]},{"id":10,"x":0.1,"incoming":[]},{"id":11,"x":0.1,"incoming":[]},{"id":12,"x":0.1,"incoming":[]},{"id":13,"x":0.1,"incoming":[]},{"id":14,"x":0.1,"incoming":[]},{"id":15,"x":0.1,"incoming":[]},{"id":16,"x":0.1,"incoming":[]},{"id":17,"x":0.1,"incoming":[]},{"id":18,"x":0.1,"incoming":[]},{"id":19,"x":0.1,"incoming":[]},{"id":20,"x":0.1,"incoming":[]}],"hidden":[],"outputs":[{"id":21,"x":0.9,"incoming":[{"fromId":0,"weight":0.49663717,"enabled":true},{"fromId":1,"weight":1.8693384,"enabled":true},{"fromId":2,"weight":-0.15300417,"enabled":true},{"fromId":3,"weight":-0.82663924,"enabled":true},{"fromId":4,"weight":-0.046852455,"enabled":true},{"fromId":5,"weight":0.3601159,"enabled":true},{"fromId":6,"weight":1.2780955,"enabled":true},{"fromId":7,"weight":0.21696311,"enabled":true},{"fromId":8,"weight":0.93317765,"enabled":true},{"fromId":9,"weight":-2.421458,"enabled":true},{"fromId":10,"weight":-0.7395519,"enabled":true},{"fromId":11,"weight":1.286233,"enabled":true},{"fromId":12,"weight":-1.5385525,"enabled":true},{"fromId":13,"weight":1.441488,"enabled":true},{"fromId":14,"weight":1.6626773,"enabled":true},{"fromId":15,"weight":1.145067,"enabled":true},{"fromId":16,"weight":-0.8839832,"enabled":true},{"fromId":17,"weight":-1.7460485,"enabled":true},{"fromId":18,"weight":-1.4328606,"enabled":true},{"fromId":19,"weight":-0.3854981,"enabled":true},{"fromId":20,"weight":0.49371362,"enabled":true}]},{"id":22,"x":0.9,"incoming":[{"fromId":0,"weight":-0.27299374,"enabled":true},{"fromId":1,"weight":-1.9697548,"enabled":true},{"fromId":2,"weight":0.08200598,"enabled":true},{"fromId":3,"weight":0.6762652,"enabled":true},{"fromId":4,"weight":0.6226963,"enabled":true},{"fromId":5,"weight":-0.22981934,"enabled":true},{"fromId":6,"weight":2.4635038,"enabled":true},{"fromId":7,"weight":1.0965171,"enabled":true},{"fromId":8,"weight":0.2027733,"enabled":true},{"fromId":9,"weight":0.88320446,"enabled":true},{"fromId":10,"weight":1.0523099,"enabled":true},{"fromId":11,"weight":-0.24926138,"enabled":true},{"fromId":12,"weight":1.0968498,"enabled":true},{"fromId":13,"weight":0.2715214,"enabled":true},{"fromId":14,"weight":-0.28372,"enabled":true},{"fromId":15,"weight":-0.6852143,"enabled":true},{"fromId":16,"weight":0.56244403,"enabled":true},{"fromId":17,"weight":1.4173781,"enabled":true},{"fromId":18,"weight":-1.4771011,"enabled":true},{"fromId":19,"weight":-0.7117761,"enabled":true},{"fromId":20,"weight":0.029364366,"enabled":true}]},{"id":23,"x":0.9,"incoming":[{"fromId":0,"weight":-0.080514655,"enabled":true},{"fromId":1,"weight":-0.887747,"enabled":true},{"fromId":2,"weight":0.9137872,"enabled":true},{"fromId":3,"weight":-0.28025627,"enabled":true},{"fromId":4,"weight":-0.24758251,"enabled":true},{"fromId":5,"weight":0.11660126,"enabled":true},{"fromId":6,"weight":-1.0896244,"enabled":true},{"fromId":7,"weight":0.5892017,"enabled":true},{"fromId":8,"weight":0.38160527,"enabled":true},{"fromId":9,"weight":0.37565404,"enabled":true},{"fromId":10,"weight":-0.35074708,"enabled":true},{"fromId":11,"weight":-1.3756264,"enabled":true},{"fromId":12,"weight":1.3758051,"enabled":true},{"fromId":13,"weight":-0.4788496,"enabled":true},{"fromId":14,"weight":-0.76468784,"enabled":true},{"fromId":15,"weight":0.5727682,"enabled":true},{"fromId":16,"weight":0.31248102,"enabled":true},{"fromId":17,"weight":0.095249906,"enabled":true},{"fromId":18,"weight":0.28271714,"enabled":true},{"fromId":19,"weight":-0.96258277,"enabled":true},{"fromId":20,"weight":-0.5390223,"enabled":true}]},{"id":24,"x":0.9,"incoming":[{"fromId":0,"weight":-0.6898887,"enabled":true},{"fromId":1,"weight":-1.0366845,"enabled":true},{"fromId":2,"weight":-0.4979489,"enabled":true},{"fromId":3,"weight":0.8526585,"enabled":true},{"fromId":4,"weight":0.18651333,"enabled":true},{"fromId":5,"weight":1.048491,"enabled":true},{"fromId":6,"weight":-0.7337692,"enabled":true},{"fromId":7,"weight":-0.93184716,"enabled":true},{"fromId":8,"weight":-1.0299293,"enabled":true},{"fromId":9,"weight":0.12765323,"enabled":true},{"fromId":10,"weight":0.65827966,"enabled":true},{"fromId":11,"weight":-1.0223233,"enabled":true},{"fromId":12,"weight":0.25563493,"enabled":true},{"fromId":13,"weight":0.07613987,"enabled":true},{"fromId":14,"weight":0.08666494,"enabled":true},{"fromId":15,"weight":-0.5107621,"enabled":true},{"fromId":16,"weight":-2.3591082,"enabled":true},{"fromId":17,"weight":-1.7189962,"enabled":true},{"fromId":18,"weight":-1.3277406,"enabled":true},{"fromId":19,"weight":-0.051320154,"enabled":true},{"fromId":20,"weight":-1.5860438,"enabled":true}]}]}