{"isAddBias":true,"inputs":[{"id":0,"x":0.1,"incoming":[]},{"id":1,"x":0.1,"incoming":[]},{"id":2,"x":0.1,"incoming":[]},{"id":3,"x":0.1,"incoming":[]},{"id":4,"x":0.1,"incoming":[]},{"id":5,"x":0.1,"incoming":[]},{"id":6,"x":0.1,"incoming":[]},{"id":7,"x":0.1,"incoming":[]},{"id":8,"x":0.1,"incoming":[]},{"id":9,"x":0.1,"incoming":[]},{"id":10,"x":0.1,"incoming":[]},{"id":11,"x":0.1,"incoming":[{"fromId":4,"weight":-0.3360563,"enabled":true},{"fromId":0,"weight":0.8063904,"enabled":true}]},{"id":12,"x":0.1,"incoming":[]},{"id":13,"x":0.1,"incoming":[]},{"id":14,"x":0.1,"incoming":[]},{"id":15,"x":0.1,"incoming":[]},{"id":16,"x":0.1,"incoming":[]},{"id":17,"x":0.1,"incoming":[]},{"id":18,"x":0.1,"incoming":[]},{"id":19,"x":0.1,"incoming":[]},{"id":20,"x":0.1,"incoming":[]}],"hidden":[{"id":312,"x":0.125,"incoming":[{"fromId":45,"weight":0.38999432,"enabled":true},{"fromId":0,"weight":-0.66924936,"enabled":true}]},{"id":178,"x":0.14999999,"incoming":[{"fromId":0,"weight":0.3237262,"enabled":true},{"fromId":13,"weight":-0.8016983,"enabled":true},{"fromId":2,"weight":0.8450686,"enabled":true}]},{"id":448,"x":0.1625,"incoming":[{"fromId":0,"weight":0.53642315,"enabled":true},{"fromId":91,"weight":0.0027249455,"enabled":true},{"fromId":2,"weight":-0.3106885,"enabled":true}]},{"id":93,"x":0.19999999,"incoming":[{"fromId":0,"weight":-0.8669431,"enabled":true},{"fromId":1,"weight":0.6507632,"enabled":true},{"fromId":178,"weight":0.27880114,"enabled":true},{"fromId":10,"weight":1.813155,"enabled":true},{"fromId":11,"weight":0.5505917,"enabled":true},{"fromId":173,"weight":-0.8933279,"enabled":true},{"fromId":184,"weight":-0.9809483,"enabled":true}]},{"id":94,"x":0.19999999,"incoming":[{"fromId":0,"weight":0.19687423,"enabled":true},{"fromId":21,"weight":0.5677462,"enabled":true},{"fromId":3,"weight":-0.08616245,"enabled":true},{"fromId":4,"weight":0.7275134,"enabled":true},{"fromId":257,"weight":0.7835527,"enabled":true},{"fromId":9,"weight":0.058221538,"enabled":true}]},{"id":253,"x":0.19999999,"incoming":[{"fromId":2,"weight":-0.40866506,"enabled":true},{"fromId":0,"weight":0.15399644,"enabled":true},{"fromId":5,"weight":-0.2860686,"enabled":true}]},{"id":150,"x":0.25,"incoming":[{"fromId":7,"weight":0.019491203,"enabled":true},{"fromId":0,"weight":-0.15349974,"enabled":true}]},{"id":179,"x":0.25,"incoming":[{"fromId":29,"weight":0.41496292,"enabled":true},{"fromId":0,"weight":0.010477051,"enabled":true}]},{"id":341,"x":0.25,"incoming":[{"fromId":2,"weight":0.18609005,"enabled":true},{"fromId":0,"weight":0.10234115,"enabled":true}]},{"id":368,"x":0.25,"incoming":[{"fromId":11,"weight":0.68652314,"enabled":true},{"fromId":0,"weight":-0.22060558,"enabled":true}]},{"id":46,"x":0.29999998,"incoming":[{"fromId":29,"weight":0.679422,"enabled":true},{"fromId":0,"weight":-0.5566367,"enabled":true},{"fromId":1,"weight":-0.20866159,"enabled":true},{"fromId":33,"weight":-0.91119176,"enabled":true},{"fromId":456,"weight":0.036269233,"enabled":true}]},{"id":47,"x":0.29999998,"incoming":[{"fromId":38,"weight":0.6214479,"enabled":true},{"fromId":0,"weight":-1.4418714,"enabled":true},{"fromId":3,"weight":-0.9963844,"enabled":true}]},{"id":58,"x":0.29999998,"incoming":[{"fromId":0,"weight":-0.16113105,"enabled":true},{"fromId":93,"weight":-0.4677524,"enabled":true},{"fromId":89,"weight":-1.7719942,"enabled":true},{"fromId":2,"weight":0.6690252,"enabled":true}]},{"id":64,"x":0.29999998,"incoming":[{"fromId":0,"weight":1.7112482,"enabled":true},{"fromId":2,"weight":-0.359764,"enabled":true},{"fromId":8,"weight":-0.047266573,"enabled":true},{"fromId":253,"weight":0.85667646,"enabled":true}]},{"id":65,"x":0.29999998,"incoming":[{"fromId":2,"weight":0.052466772,"enabled":true},{"fromId":0,"weight":0.5253207,"enabled":true},{"fromId":1,"weight":-0.97624314,"enabled":true},{"fromId":12,"weight":0.3189231,"enabled":true}]},{"id":68,"x":0.29999998,"incoming":[{"fromId":0,"weight":0.95960844,"enabled":true},{"fromId":8,"weight":2.1329234,"enabled":true}]},{"id":69,"x":0.29999998,"incoming":[{"fromId":8,"weight":-1.7729012,"enabled":true},{"fromId":0,"weight":1.427347,"enabled":true}]},{"id":84,"x":0.29999998,"incoming":[{"fromId":0,"weight":-0.03198491,"enabled":true},{"fromId":2,"weight":0.0963269,"enabled":true}]},{"id":85,"x":0.29999998,"incoming":[{"fromId":82,"weight":0.850211,"enabled":true},{"fromId":0,"weight":0.14994636,"enabled":true}]},{"id":102,"x":0.29999998,"incoming":[{"fromId":0,"weight":-0.39377174,"enabled":true},{"fromId":33,"weight":0.6355951,"enabled":true},{"fromId":16,"weight":-0.96330774,"enabled":true}]},{"id":116,"x":0.29999998,"incoming":[{"fromId":40,"weight":0.4445464,"enabled":true},{"fromId":0,"weight":-0.07490672,"enabled":true}]},{"id":126,"x":0.29999998,"incoming":[{"fromId":0,"weight":-1.1467862,"enabled":true}]},{"id":133,"x":0.29999998,"incoming":[{"fromId":8,"weight":-0.12842274,"enabled":true},{"fromId":0,"weight":-0.191425,"enabled":true}]},{"id":135,"x":0.29999998,"incoming":[{"fromId":1,"weight":0.30371755,"enabled":true},{"fromId":0,"weight":-0.32098836,"enabled":true},{"fromId":7,"weight":0.8864525,"enabled":true},{"fromId":11,"weight":-1.495038,"enabled":true}]},{"id":145,"x":0.29999998,"incoming":[{"fromId":7,"weight":-0.52067447,"enabled":true},{"fromId":0,"weight":-0.0257283,"enabled":true}]},{"id":148,"x":0.29999998,"incoming":[{"fromId":26,"weight":-0.7908585,"enabled":true},{"fromId":0,"weight":1.0603781,"enabled":true}]},{"id":171,"x":0.29999998,"incoming":[{"fromId":65,"weight":-0.20395482,"enabled":true},{"fromId":0,"weight":0.8996786,"enabled":true}]},{"id":173,"x":0.29999998,"incoming":[{"fromId":0,"weight":1.1649723,"enabled":true},{"fromId":8,"weight":-0.18375504,"enabled":true}]},{"id":175,"x":0.29999998,"incoming":[{"fromId":5,"weight":0.51097023,"enabled":true},{"fromId":0,"weight":-0.41246468,"enabled":true},{"fromId":6,"weight":0.90331525,"enabled":true},{"fromId":312,"weight":-0.6779807,"enabled":true}]},{"id":189,"x":0.29999998,"incoming":[{"fromId":5,"weight":-2.517098,"enabled":true},{"fromId":0,"weight":-0.069392994,"enabled":true},{"fromId":150,"weight":-1.1439149,"enabled":true}]},{"id":214,"x":0.29999998,"incoming":[{"fromId":2,"weight":0.5455728,"enabled":true},{"fromId":0,"weight":0.9091203,"enabled":true},{"fromId":6,"weight":-0.12488696,"enabled":true}]},{"id":222,"x":0.29999998,"incoming":[{"fromId":7,"weight":-0.32081807,"enabled":true},{"fromId":0,"weight":0.44493875,"enabled":true},{"fromId":4,"weight":0.4880917,"enabled":true},{"fromId":18,"weight":-0.031409033,"enabled":true}]},{"id":238,"x":0.29999998,"incoming":[{"fromId":0,"weight":-0.10803945,"enabled":true},{"fromId":149,"weight":-0.59564775,"enabled":true},{"fromId":2,"weight":-0.35154092,"enabled":true},{"fromId":408,"weight":-0.39661032,"enabled":true}]},{"id":377,"x":0.29999998,"incoming":[{"fromId":3,"weight":-0.0041271746,"enabled":true},{"fromId":0,"weight":0.85011333,"enabled":true},{"fromId":188,"weight":0.40701878,"enabled":true}]},{"id":407,"x":0.29999998,"incoming":[{"fromId":2,"weight":-0.120026715,"enabled":true},{"fromId":0,"weight":0.6394328,"enabled":true}]},{"id":188,"x":0.325,"incoming":[{"fromId":0,"weight":-1.0782243,"enabled":true},{"fromId":5,"weight":0.4941355,"enabled":true}]},{"id":351,"x":0.325,"incoming":[{"fromId":94,"weight":-0.9229813,"enabled":true},{"fromId":0,"weight":-0.4071577,"enabled":true},{"fromId":21,"weight":0.39680862,"enabled":true}]},{"id":370,"x":0.34999996,"incoming":[{"fromId":94,"weight":-0.07974782,"enabled":true},{"fromId":0,"weight":-0.16377692,"enabled":true}]},{"id":381,"x":0.34999996,"incoming":[{"fromId":145,"weight":1.2507381,"enabled":true},{"fromId":0,"weight":-1.089833,"enabled":true},{"fromId":148,"weight":1.3446355,"enabled":true}]},{"id":240,"x":0.35,"incoming":[{"fromId":1,"weight":1.9254963,"enabled":true},{"fromId":0,"weight":0.7223072,"enabled":true},{"fromId":145,"weight":0.8570657,"enabled":true}]},{"id":270,"x":0.35,"incoming":[{"fromId":9,"weight":-0.6407784,"enabled":true},{"fromId":0,"weight":-1.0822551,"enabled":true},{"fromId":7,"weight":0.030905373,"enabled":true}]},{"id":395,"x":0.35,"incoming":[{"fromId":85,"weight":0.6395102,"enabled":true},{"fromId":0,"weight":0.286803,"enabled":true}]},{"id":456,"x":0.35,"incoming":[{"fromId":1,"weight":0.42815173,"enabled":true},{"fromId":0,"weight":0.18263265,"enabled":true}]},{"id":80,"x":0.39999998,"incoming":[{"fromId":5,"weight":-0.698204,"enabled":true},{"fromId":0,"weight":-1.2375987,"enabled":true},{"fromId":2,"weight":0.5621601,"enabled":true},{"fromId":4,"weight":-1.015933,"enabled":true}]},{"id":97,"x":0.39999998,"incoming":[{"fromId":29,"weight":0.7473022,"enabled":true},{"fromId":0,"weight":0.5846616,"enabled":true},{"fromId":2,"weight":-0.47477025,"enabled":true},{"fromId":13,"weight":-0.3836444,"enabled":true},{"fromId":10,"weight":0.9794533,"enabled":true},{"fromId":179,"weight":2.1674886,"enabled":true},{"fromId":220,"weight":-0.6043837,"enabled":true},{"fromId":11,"weight":0.05039237,"enabled":true},{"fromId":32,"weight":0.4967637,"enabled":true},{"fromId":341,"weight":0.07337053,"enabled":true},{"fromId":240,"weight":0.42080268,"enabled":true}]},{"id":100,"x":0.39999998,"incoming":[{"fromId":31,"weight":1.6520112,"enabled":true},{"fromId":0,"weight":0.43736503,"enabled":true}]},{"id":114,"x":0.39999998,"incoming":[{"fromId":7,"weight":0.20580533,"enabled":true},{"fromId":0,"weight":-0.45876646,"enabled":true},{"fromId":150,"weight":7.1836775E-4,"enabled":true},{"fromId":13,"weight":-0.3616243,"enabled":true},{"fromId":58,"weight":-2.025648,"enabled":true},{"fromId":145,"weight":0.31774712,"enabled":true},{"fromId":381,"weight":-0.31667277,"enabled":true}]},{"id":123,"x":0.39999998,"incoming":[{"fromId":65,"weight":0.5624707,"enabled":true},{"fromId":0,"weight":-0.7899555,"enabled":true},{"fromId":8,"weight":1.0787046,"enabled":true},{"fromId":171,"weight":-0.9233302,"enabled":true}]},{"id":167,"x":0.39999998,"incoming":[{"fromId":7,"weight":1.233204,"enabled":true},{"fromId":6,"weight":-0.53375494,"enabled":true},{"fromId":0,"weight":0.28439495,"enabled":true},{"fromId":1,"weight":-0.8162057,"enabled":true},{"fromId":341,"weight":-0.36944288,"enabled":true}]},{"id":220,"x":0.39999998,"incoming":[{"fromId":13,"weight":0.34317315,"enabled":true},{"fromId":0,"weight":-0.24172965,"enabled":true}]},{"id":230,"x":0.39999998,"incoming":[{"fromId":64,"weight":0.2112196,"enabled":true},{"fromId":0,"weight":0.022337511,"enabled":true},{"fromId":102,"weight":-0.4854852,"enabled":true},{"fromId":473,"weight":1.0640792,"enabled":true}]},{"id":257,"x":0.39999998,"incoming":[{"fromId":21,"weight":-1.0417886,"enabled":true},{"fromId":0,"weight":0.6725069,"enabled":true},{"fromId":12,"weight":0.6270338,"enabled":true},{"fromId":94,"weight":-0.805956,"enabled":true}]},{"id":291,"x":0.39999998,"incoming":[{"fromId":11,"weight":0.6497711,"enabled":true},{"fromId":0,"weight":-1.4398744,"enabled":true},{"fromId":368,"weight":0.61228836,"enabled":true},{"fromId":270,"weight":-0.10123105,"enabled":true}]},{"id":508,"x":0.42499995,"incoming":[{"fromId":47,"weight":1.4365768,"enabled":true},{"fromId":0,"weight":-0.41368514,"enabled":true}]},{"id":290,"x":0.42499998,"incoming":[{"fromId":0,"weight":-1.0005894,"enabled":true},{"fromId":11,"weight":0.2992913,"enabled":true}]},{"id":311,"x":0.425,"incoming":[{"fromId":178,"weight":-0.29066956,"enabled":true},{"fromId":0,"weight":0.41467172,"enabled":true},{"fromId":189,"weight":-0.38316175,"enabled":true}]},{"id":379,"x":0.425,"incoming":[{"fromId":178,"weight":0.19487062,"enabled":true},{"fromId":0,"weight":0.5833683,"enabled":true},{"fromId":58,"weight":-0.9007782,"enabled":true}]},{"id":380,"x":0.44999996,"incoming":[{"fromId":3,"weight":-0.71204937,"enabled":true},{"fromId":0,"weight":0.6856304,"enabled":true},{"fromId":145,"weight":-0.09712875,"enabled":true}]},{"id":202,"x":0.45,"incoming":[{"fromId":94,"weight":0.08122611,"enabled":true},{"fromId":0,"weight":-0.093502924,"enabled":true},{"fromId":351,"weight":-0.41857123,"enabled":true},{"fromId":257,"weight":0.82157654,"enabled":true},{"fromId":1,"weight":1.6429807,"enabled":true}]},{"id":204,"x":0.45,"incoming":[{"fromId":123,"weight":-0.24197857,"enabled":true},{"fromId":0,"weight":-0.024579331,"enabled":true}]},{"id":362,"x":0.45,"incoming":[{"fromId":167,"weight":0.76590914,"enabled":true},{"fromId":0,"weight":1.0730238,"enabled":true}]},{"id":363,"x":0.45,"incoming":[{"fromId":47,"weight":1.2617836,"enabled":true},{"fromId":0,"weight":-0.14497828,"enabled":true}]},{"id":473,"x":0.46249998,"incoming":[{"fromId":64,"weight":0.5694216,"enabled":true},{"fromId":0,"weight":0.70606935,"enabled":true}]},{"id":25,"x":0.49999997,"incoming":[{"fromId":1,"weight":0.2507625,"enabled":true},{"fromId":0,"weight":-0.63751984,"enabled":true},{"fromId":3,"weight":1.4447343,"enabled":true},{"fromId":2,"weight":0.40288156,"enabled":true},{"fromId":4,"weight":-1.8118033,"enabled":true},{"fromId":8,"weight":-0.49478978,"enabled":true},{"fromId":65,"weight":0.5149622,"enabled":false},{"fromId":69,"weight":-1.2395436,"enabled":true},{"fromId":7,"weight":-0.4591658,"enabled":true},{"fromId":123,"weight":0.042169765,"enabled":true},{"fromId":5,"weight":-1.5054631,"enabled":true},{"fromId":68,"weight":-0.9943005,"enabled":true},{"fromId":64,"weight":-0.33473292,"enabled":true},{"fromId":175,"weight":-1.2825384,"enabled":true},{"fromId":11,"weight":-1.7012842,"enabled":true},{"fromId":38,"weight":-0.19781002,"enabled":true},{"fromId":109,"weight":-0.1843187,"enabled":true},{"fromId":230,"weight":0.24213609,"enabled":true},{"fromId":45,"weight":0.40814447,"enabled":true},{"fromId":119,"weight":0.5736747,"enabled":false},{"fromId":287,"weight":0.7343002,"enabled":true},{"fromId":360,"weight":2.2720544,"enabled":true},{"fromId":133,"weight":-0.6787925,"enabled":true},{"fromId":290,"weight":-0.9452181,"enabled":true},{"fromId":416,"weight":0.3342057,"enabled":true},{"fromId":112,"weight":1.0697954,"enabled":false}]},{"id":26,"x":0.49999997,"incoming":[{"fromId":4,"weight":-1.1437167,"enabled":true},{"fromId":0,"weight":0.06354153,"enabled":true},{"fromId":8,"weight":-0.2899387,"enabled":true},{"fromId":6,"weight":-0.48034185,"enabled":true},{"fromId":5,"weight":-1.1255391,"enabled":true},{"fromId":1,"weight":0.17973697,"enabled":true},{"fromId":3,"weight":0.833684,"enabled":true},{"fromId":2,"weight":-0.63378906,"enabled":true},{"fromId":168,"weight":-0.16669731,"enabled":true},{"fromId":141,"weight":-0.19434628,"enabled":true},{"fromId":167,"weight":-0.28859347,"enabled":true},{"fromId":189,"weight":0.44725996,"enabled":true},{"fromId":362,"weight":0.007553458,"enabled":true}]},{"id":27,"x":0.49999997,"incoming":[{"fromId":0,"weight":0.60550547,"enabled":true},{"fromId":2,"weight":-0.023785546,"enabled":true},{"fromId":3,"weight":-1.1294112,"enabled":true},{"fromId":7,"weight":0.89917386,"enabled":true},{"fromId":214,"weight":1.2132165,"enabled":true},{"fromId":1,"weight":0.71414953,"enabled":true},{"fromId":102,"weight":0.6581898,"enabled":true},{"fromId":253,"weight":0.09322798,"enabled":true}]},{"id":29,"x":0.49999997,"incoming":[{"fromId":0,"weight":1.7573757,"enabled":true},{"fromId":8,"weight":0.20968568,"enabled":true},{"fromId":5,"weight":0.19290495,"enabled":true},{"fromId":1,"weight":-0.2743401,"enabled":true},{"fromId":6,"weight":0.39999652,"enabled":true},{"fromId":189,"weight":0.06858115,"enabled":true},{"fromId":39,"weight":0.85354286,"enabled":true},{"fromId":105,"weight":-0.21273255,"enabled":true},{"fromId":12,"weight":-0.87087923,"enabled":true},{"fromId":356,"weight":0.2632879,"enabled":true},{"fromId":188,"weight":-0.15266603,"enabled":false},{"fromId":202,"weight":0.157768,"enabled":true},{"fromId":377,"weight":0.6725676,"enabled":true}]},{"id":30,"x":0.49999997,"incoming":[{"fromId":3,"weight":-0.11897814,"enabled":true},{"fromId":0,"weight":-0.9342018,"enabled":true},{"fromId":377,"weight":-1.2374368,"enabled":true},{"fromId":395,"weight":-1.8678133,"enabled":true}]},{"id":31,"x":0.49999997,"incoming":[{"fromId":0,"weight":-1.7892823,"enabled":true},{"fromId":8,"weight":0.23722704,"enabled":true},{"fromId":63,"weight":-0.6998242,"enabled":true},{"fromId":3,"weight":-1.4288065,"enabled":true}]},{"id":32,"x":0.49999997,"incoming":[{"fromId":3,"weight":-0.30444443,"enabled":true},{"fromId":0,"weight":-1.2650032,"enabled":true},{"fromId":1,"weight":0.12079844,"enabled":true},{"fromId":65,"weight":0.6267423,"enabled":true}]},{"id":33,"x":0.49999997,"incoming":[{"fromId":1,"weight":0.20562896,"enabled":true},{"fromId":0,"weight":0.9934522,"enabled":true},{"fromId":7,"weight":-0.64931214,"enabled":true},{"fromId":5,"weight":1.3912517,"enabled":true},{"fromId":8,"weight":0.072505385,"enabled":true},{"fromId":84,"weight":0.03347842,"enabled":true},{"fromId":123,"weight":-1.3943766,"enabled":true},{"fromId":11,"weight":0.24607535,"enabled":true},{"fromId":222,"weight":-0.78116965,"enabled":true}]},{"id":35,"x":0.49999997,"incoming":[{"fromId":2,"weight":0.065630436,"enabled":true},{"fromId":0,"weight":-0.7850824,"enabled":true},{"fromId":407,"weight":-0.2059975,"enabled":true},{"fromId":290,"weight":0.087954566,"enabled":true}]},{"id":36,"x":0.49999997,"incoming":[{"fromId":2,"weight":0.004830223,"enabled":true},{"fromId":0,"weight":-1.4403305,"enabled":true},{"fromId":94,"weight":0.12204692,"enabled":true},{"fromId":370,"weight":0.14892142,"enabled":true},{"fromId":14,"weight":0.108371586,"enabled":true}]},{"id":37,"x":0.49999997,"incoming":[{"fromId":1,"weight":-0.79629606,"enabled":true},{"fromId":0,"weight":-0.6464555,"enabled":true},{"fromId":5,"weight":-0.42972273,"enabled":true},{"fromId":65,"weight":-2.0414107,"enabled":true},{"fromId":3,"weight":0.899822,"enabled":true},{"fromId":114,"weight":0.066533536,"enabled":true},{"fromId":84,"weight":0.03457543,"enabled":true},{"fromId":58,"weight":-0.9014238,"enabled":true}]},{"id":40,"x":0.49999997,"incoming":[{"fromId":3,"weight":-1.0522797,"enabled":true},{"fromId":0,"weight":0.8820434,"enabled":true},{"fromId":2,"weight":0.22407639,"enabled":true},{"fromId":9,"weight":-0.054623492,"enabled":true},{"fromId":8,"weight":0.87134016,"enabled":true},{"fromId":37,"weight":0.6698472,"enabled":true},{"fromId":270,"weight":-0.34589186,"enabled":true}]},{"id":41,"x":0.49999997,"incoming":[{"fromId":2,"weight":-0.21943083,"enabled":true},{"fromId":0,"weight":0.6661092,"enabled":true},{"fromId":84,"weight":-0.60549533,"enabled":true},{"fromId":6,"weight":-0.7852361,"enabled":true}]},{"id":42,"x":0.49999997,"incoming":[{"fromId":1,"weight":0.30491558,"enabled":true},{"fromId":0,"weight":-1.8004049,"enabled":true},{"fromId":4,"weight":-0.6215615,"enabled":true},{"fromId":5,"weight":-0.568656,"enabled":true},{"fromId":13,"weight":-0.11085832,"enabled":true},{"fromId":84,"weight":-0.19674951,"enabled":true},{"fromId":11,"weight":0.89519286,"enabled":true},{"fromId":64,"weight":-0.110674724,"enabled":true},{"fromId":3,"weight":1.2279882,"enabled":true},{"fromId":12,"weight":-1.3733184,"enabled":true},{"fromId":98,"weight":-0.29931808,"enabled":true},{"fromId":58,"weight":-0.9101517,"enabled":true}]},{"id":45,"x":0.49999997,"incoming":[{"fromId":0,"weight":-0.6962288,"enabled":true},{"fromId":3,"weight":0.11783031,"enabled":true},{"fromId":7,"weight":0.7991087,"enabled":true},{"fromId":114,"weight":-1.2194251,"enabled":true},{"fromId":189,"weight":0.009752288,"enabled":true},{"fromId":126,"weight":-0.07785525,"enabled":true}]},{"id":49,"x":0.49999997,"incoming":[{"fromId":0,"weight":-0.18390322,"enabled":true},{"fromId":58,"weight":0.18128948,"enabled":true},{"fromId":6,"weight":0.06785768,"enabled":true},{"fromId":57,"weight":0.3115657,"enabled":true},{"fromId":80,"weight":-0.1349857,"enabled":true},{"fromId":123,"weight":0.5012217,"enabled":true},{"fromId":97,"weight":0.8854802,"enabled":true},{"fromId":204,"weight":-0.84248006,"enabled":true},{"fromId":10,"weight":-1.12136,"enabled":true},{"fromId":167,"weight":0.33197546,"enabled":true},{"fromId":175,"weight":-1.0265988,"enabled":true},{"fromId":311,"weight":-0.63276404,"enabled":true}]},{"id":56,"x":0.49999997,"incoming":[{"fromId":49,"weight":0.040052913,"enabled":true},{"fromId":0,"weight":-0.9899415,"enabled":true},{"fromId":214,"weight":-1.241915,"enabled":true}]},{"id":89,"x":0.49999997,"incoming":[{"fromId":0,"weight":-0.50424236,"enabled":true},{"fromId":238,"weight":-1.2306437,"enabled":true},{"fromId":42,"weight":0.12968248,"enabled":true}]},{"id":138,"x":0.49999997,"incoming":[{"fromId":8,"weight":0.2581663,"enabled":true},{"fromId":0,"weight":0.16021658,"enabled":true},{"fromId":102,"weight":0.62644166,"enabled":true}]},{"id":182,"x":0.49999997,"incoming":[{"fromId":11,"weight":0.39070326,"enabled":true},{"fromId":0,"weight":0.1287761,"enabled":true}]},{"id":215,"x":0.49999997,"incoming":[{"fromId":45,"weight":-0.94920427,"enabled":true},{"fromId":0,"weight":1.4728538,"enabled":true},{"fromId":133,"weight":-0.0761325,"enabled":true},{"fromId":68,"weight":-0.29140702,"enabled":true},{"fromId":312,"weight":0.04948455,"enabled":true}]},{"id":227,"x":0.49999997,"incoming":[{"fromId":6,"weight":0.26293665,"enabled":true},{"fromId":0,"weight":2.1890676,"enabled":true},{"fromId":14,"weight":0.10005941,"enabled":true}]},{"id":294,"x":0.49999997,"incoming":[{"fromId":80,"weight":0.034341276,"enabled":true},{"fromId":0,"weight":-0.50331557,"enabled":true}]},{"id":331,"x":0.49999997,"incoming":[{"fromId":7,"weight":0.26598158,"enabled":true},{"fromId":0,"weight":0.0029257461,"enabled":true}]},{"id":285,"x":0.5,"incoming":[{"fromId":0,"weight":0.61642516,"enabled":true},{"fromId":11,"weight":-0.519028,"enabled":true}]},{"id":302,"x":0.5,"incoming":[{"fromId":189,"weight":-0.9256181,"enabled":true},{"fromId":0,"weight":2.1486964,"enabled":true},{"fromId":53,"weight":-0.98517334,"enabled":true}]},{"id":303,"x":0.5,"incoming":[{"fromId":102,"weight":-0.83157736,"enabled":true},{"fromId":0,"weight":-1.0185255,"enabled":true},{"fromId":10,"weight":-0.09843677,"enabled":true}]},{"id":408,"x":0.5,"incoming":[{"fromId":149,"weight":-0.9192477,"enabled":true},{"fromId":0,"weight":-1.5322678,"enabled":true},{"fromId":294,"weight":-0.08233686,"enabled":true}]},{"id":410,"x":0.525,"incoming":[{"fromId":40,"weight":-0.632901,"enabled":true},{"fromId":0,"weight":-1.6348487,"enabled":true}]},{"id":510,"x":0.525,"incoming":[{"fromId":85,"weight":-0.10046199,"enabled":true},{"fromId":0,"weight":-0.69739825,"enabled":true}]},{"id":536,"x":0.53749996,"incoming":[{"fromId":410,"weight":0.60247314,"enabled":true},{"fromId":0,"weight":1.1306742,"enabled":true}]},{"id":152,"x":0.54999995,"incoming":[{"fromId":27,"weight":-1.5291166,"enabled":true},{"fromId":0,"weight":0.24349141,"enabled":true}]},{"id":265,"x":0.54999995,"incoming":[{"fromId":40,"weight":0.7823628,"enabled":true},{"fromId":0,"weight":-0.21055615,"enabled":true},{"fromId":138,"weight":-0.40912205,"enabled":true},{"fromId":410,"weight":-0.06518975,"enabled":true},{"fromId":536,"weight":-0.6115774,"enabled":true}]},{"id":306,"x":0.54999995,"incoming":[{"fromId":123,"weight":0.8357966,"enabled":true},{"fromId":0,"weight":0.5360485,"enabled":true}]},{"id":347,"x":0.54999995,"incoming":[{"fromId":65,"weight":-0.34042722,"enabled":true},{"fromId":40,"weight":-0.67130387,"enabled":true},{"fromId":0,"weight":-0.39370567,"enabled":true},{"fromId":47,"weight":-0.9722308,"enabled":true},{"fromId":508,"weight":-0.19140898,"enabled":true}]},{"id":360,"x":0.54999995,"incoming":[{"fromId":109,"weight":-0.47630435,"enabled":true},{"fromId":0,"weight":0.97087187,"enabled":true},{"fromId":362,"weight":0.49076116,"enabled":true}]},{"id":416,"x":0.54999995,"incoming":[{"fromId":230,"weight":0.14336345,"enabled":true},{"fromId":0,"weight":0.43406907,"enabled":true}]},{"id":249,"x":0.575,"incoming":[{"fromId":0,"weight":1.0930451,"enabled":true},{"fromId":88,"weight":0.89961445,"enabled":true}]},{"id":389,"x":0.575,"incoming":[{"fromId":31,"weight":-0.381076,"enabled":true},{"fromId":0,"weight":-0.36056137,"enabled":true}]},{"id":82,"x":0.59999996,"incoming":[{"fromId":31,"weight":-0.096099615,"enabled":true},{"fromId":0,"weight":2.7380152,"enabled":true},{"fromId":105,"weight":-2.0524142,"enabled":true},{"fromId":26,"weight":0.19742304,"enabled":true},{"fromId":9,"weight":1.5709903,"enabled":true},{"fromId":42,"weight":-0.4313082,"enabled":true},{"fromId":1,"weight":0.4035278,"enabled":true},{"fromId":85,"weight":-1.2429907,"enabled":true},{"fromId":149,"weight":0.42494804,"enabled":true},{"fromId":100,"weight":0.46896043,"enabled":true},{"fromId":148,"weight":-1.3711786,"enabled":true},{"fromId":40,"weight":0.45654055,"enabled":true},{"fromId":265,"weight":0.54389375,"enabled":true}]},{"id":88,"x":0.59999996,"incoming":[{"fromId":6,"weight":-0.0896505,"enabled":true},{"fromId":0,"weight":-0.31792668,"enabled":true},{"fromId":1,"weight":-0.10321933,"enabled":true},{"fromId":13,"weight":-1.031107,"enabled":true},{"fromId":2,"weight":-1.1471105,"enabled":true},{"fromId":240,"weight":-0.23649006,"enabled":true}]},{"id":98,"x":0.59999996,"incoming":[{"fromId":32,"weight":-0.053414047,"enabled":true},{"fromId":0,"weight":-0.247244,"enabled":true},{"fromId":5,"weight":-0.0134466365,"enabled":true},{"fromId":89,"weight":0.13985425,"enabled":true},{"fromId":2,"weight":-1.110627,"enabled":true}]},{"id":107,"x":0.59999996,"incoming":[{"fromId":51,"weight":1.243168,"enabled":true},{"fromId":33,"weight":-0.17099556,"enabled":true},{"fromId":25,"weight":-0.5898445,"enabled":true}]},{"id":109,"x":0.59999996,"incoming":[{"fromId":69,"weight":-0.8931968,"enabled":true},{"fromId":0,"weight":0.015055507,"enabled":true},{"fromId":9,"weight":-0.35044867,"enabled":true},{"fromId":11,"weight":-0.091795355,"enabled":true},{"fromId":182,"weight":-1.2366523,"enabled":true}]},{"id":121,"x":0.59999996,"incoming":[{"fromId":40,"weight":0.5066532,"enabled":true},{"fromId":0,"weight":-1.0933819,"enabled":true},{"fromId":26,"weight":1.515972,"enabled":true},{"fromId":80,"weight":1.5069182,"enabled":true},{"fromId":7,"weight":-0.28062963,"enabled":true},{"fromId":3,"weight":-1.0329036,"enabled":true},{"fromId":294,"weight":0.41215152,"enabled":true},{"fromId":69,"weight":0.6015448,"enabled":true},{"fromId":6,"weight":0.8243084,"enabled":true},{"fromId":408,"weight":-0.18258415,"enabled":true}]},{"id":168,"x":0.59999996,"incoming":[{"fromId":0,"weight":-0.3128337,"enabled":true},{"fromId":1,"weight":-0.6244303,"enabled":true},{"fromId":4,"weight":-1.1845698,"enabled":true},{"fromId":25,"weight":-1.4404196,"enabled":true},{"fromId":33,"weight":1.0368818,"enabled":true},{"fromId":363,"weight":-0.6081728,"enabled":true}]},{"id":184,"x":0.59999996,"incoming":[{"fromId":0,"weight":-0.9683039,"enabled":true},{"fromId":178,"weight":-0.59212023,"enabled":true}]},{"id":201,"x":0.59999996,"incoming":[{"fromId":40,"weight":-0.4352516,"enabled":true},{"fromId":0,"weight":1.2854366,"enabled":true},{"fromId":4,"weight":1.2030468,"enabled":true}]},{"id":231,"x":0.59999996,"incoming":[{"fromId":37,"weight":-1.1665375,"enabled":true},{"fromId":0,"weight":-0.31075463,"enabled":true},{"fromId":10,"weight":-0.42022848,"enabled":true},{"fromId":88,"weight":-0.8220247,"enabled":true},{"fromId":85,"weight":-0.44539636,"enabled":true},{"fromId":135,"weight":-0.1818412,"enabled":true},{"fromId":371,"weight":0.23866004,"enabled":true},{"fromId":395,"weight":1.1403725,"enabled":true}]},{"id":266,"x":0.59999996,"incoming":[{"fromId":40,"weight":-0.28658694,"enabled":true},{"fromId":0,"weight":-1.4832745,"enabled":true},{"fromId":347,"weight":-0.6815176,"enabled":true},{"fromId":360,"weight":0.68891805,"enabled":true},{"fromId":85,"weight":-0.16020077,"enabled":true}]},{"id":282,"x":0.59999996,"incoming":[{"fromId":29,"weight":-1.189856,"enabled":true},{"fromId":0,"weight":-0.3657529,"enabled":true}]},{"id":337,"x":0.59999996,"incoming":[{"fromId":45,"weight":-0.9191874,"enabled":true},{"fromId":0,"weight":0.49435523,"enabled":true},{"fromId":13,"weight":1.1744696,"enabled":true},{"fromId":114,"weight":-0.7634701,"enabled":true},{"fromId":381,"weight":-0.032367222,"enabled":true}]},{"id":365,"x":0.59999996,"incoming":[{"fromId":45,"weight":0.9986516,"enabled":true},{"fromId":0,"weight":-0.81423616,"enabled":true},{"fromId":303,"weight":0.018966908,"enabled":true},{"fromId":33,"weight":0.160216,"enabled":true}]},{"id":371,"x":0.59999996,"incoming":[{"fromId":88,"weight":1.0242177,"enabled":true},{"fromId":0,"weight":-0.69868386,"enabled":true},{"fromId":27,"weight":-1.7808272,"enabled":true}]},{"id":393,"x":0.59999996,"incoming":[{"fromId":25,"weight":-0.03888829,"enabled":true},{"fromId":0,"weight":0.33422118,"enabled":true},{"fromId":33,"weight":-0.7884227,"enabled":true}]},{"id":136,"x":0.6,"incoming":[{"fromId":82,"weight":-0.24101198,"enabled":true},{"fromId":0,"weight":0.23509228,"enabled":true},{"fromId":102,"weight":0.71256465,"enabled":true},{"fromId":331,"weight":-1.0729473,"enabled":true}]},{"id":194,"x":0.6,"incoming":[{"fromId":46,"weight":0.5583814,"enabled":true},{"fromId":0,"weight":1.1810303,"enabled":true},{"fromId":65,"weight":-0.7110317,"enabled":true},{"fromId":270,"weight":-0.9083154,"enabled":true}]},{"id":305,"x":0.6,"incoming":[{"fromId":175,"weight":-0.03882906,"enabled":true},{"fromId":0,"weight":0.5718192,"enabled":true}]},{"id":317,"x":0.6,"incoming":[{"fromId":47,"weight":-1.6520053,"enabled":true},{"fromId":0,"weight":0.7980174,"enabled":true},{"fromId":363,"weight":1.3183767,"enabled":true},{"fromId":9,"weight":0.45407307,"enabled":true}]},{"id":556,"x":0.6,"incoming":[{"fromId":133,"weight":1.6023589,"enabled":true},{"fromId":0,"weight":-0.2260924,"enabled":true}]},{"id":568,"x":0.61249995,"incoming":[{"fromId":82,"weight":-0.37691924,"enabled":true},{"fromId":0,"weight":-2.0820427,"enabled":true}]},{"id":375,"x":0.625,"incoming":[{"fromId":82,"weight":0.3026798,"enabled":true},{"fromId":0,"weight":-0.17155275,"enabled":true},{"fromId":389,"weight":-0.8033372,"enabled":true},{"fromId":568,"weight":-0.3080001,"enabled":true}]},{"id":164,"x":0.65,"incoming":[{"fromId":31,"weight":-0.28677067,"enabled":true},{"fromId":0,"weight":0.5196437,"enabled":true},{"fromId":49,"weight":-0.99208903,"enabled":true},{"fromId":58,"weight":-0.7642582,"enabled":true},{"fromId":33,"weight":-1.4720168,"enabled":true},{"fromId":389,"weight":-0.03191206,"enabled":true},{"fromId":9,"weight":-1.4345765,"enabled":true},{"fromId":56,"weight":-0.10611367,"enabled":true}]},{"id":235,"x":0.65,"incoming":[{"fromId":82,"weight":-0.39871216,"enabled":true},{"fromId":0,"weight":0.040290095,"enabled":true},{"fromId":65,"weight":-0.2723444,"enabled":true},{"fromId":375,"weight":-1.4970651,"enabled":true},{"fromId":42,"weight":1.61762,"enabled":true}]},{"id":286,"x":0.65,"incoming":[{"fromId":0,"weight":0.079556435,"enabled":true},{"fromId":201,"weight":0.1514597,"enabled":true},{"fromId":35,"weight":-0.56834114,"enabled":true},{"fromId":4,"weight":-0.2595275,"enabled":true}]},{"id":287,"x":0.65,"incoming":[{"fromId":123,"weight":1.2113818,"enabled":true},{"fromId":0,"weight":-0.013677627,"enabled":true},{"fromId":362,"weight":0.33029425,"enabled":true}]},{"id":356,"x":0.65,"incoming":[{"fromId":105,"weight":-0.7254772,"enabled":true},{"fromId":0,"weight":-0.6716079,"enabled":true},{"fromId":135,"weight":0.7578068,"enabled":true},{"fromId":291,"weight":0.02701953,"enabled":true}]},{"id":385,"x":0.65,"incoming":[{"fromId":282,"weight":-0.46461883,"enabled":true},{"fromId":0,"weight":0.03771338,"enabled":true}]},{"id":256,"x":0.6999999,"incoming":[{"fromId":88,"weight":0.43870714,"enabled":true},{"fromId":0,"weight":0.04528963,"enabled":true}]},{"id":38,"x":0.7,"incoming":[{"fromId":1,"weight":-1.0315888,"enabled":true},{"fromId":0,"weight":-1.257187,"enabled":true},{"fromId":5,"weight":-0.12130593,"enabled":true},{"fromId":80,"weight":-1.7105149,"enabled":true},{"fromId":49,"weight":0.50431824,"enabled":true},{"fromId":65,"weight":-0.13039613,"enabled":true},{"fromId":56,"weight":1.0614973,"enabled":true},{"fromId":9,"weight":-1.6413455,"enabled":true},{"fromId":31,"weight":-1.0598328,"enabled":true},{"fromId":189,"weight":0.48732,"enabled":true},{"fromId":302,"weight":-0.2058103,"enabled":true},{"fromId":8,"weight":0.3456304,"enabled":true},{"fromId":179,"weight":0.5696175,"enabled":true}]},{"id":39,"x":0.7,"incoming":[{"fromId":2,"weight":-1.2330046,"enabled":true},{"fromId":0,"weight":-0.24770486,"enabled":true},{"fromId":40,"weight":-0.48746023,"enabled":true},{"fromId":121,"weight":-0.47857627,"enabled":true},{"fromId":88,"weight":-0.38170707,"enabled":true},{"fromId":58,"weight":-0.667437,"enabled":true},{"fromId":5,"weight":0.42131078,"enabled":true},{"fromId":49,"weight":-0.6723819,"enabled":true},{"fromId":89,"weight":-0.5252708,"enabled":true},{"fromId":27,"weight":0.5781598,"enabled":true},{"fromId":116,"weight":-1.0185091,"enabled":true},{"fromId":214,"weight":-0.7465191,"enabled":true},{"fromId":212,"weight":1.235831,"enabled":true}]},{"id":51,"x":0.7,"incoming":[{"fromId":29,"weight":1.1486931,"enabled":true},{"fromId":0,"weight":1.3524603,"enabled":true},{"fromId":97,"weight":0.4553026,"enabled":true},{"fromId":40,"weight":1.8310764,"enabled":true},{"fromId":1,"weight":-1.3711112,"enabled":true},{"fromId":135,"weight":0.9392741,"enabled":true},{"fromId":201,"weight":0.21873954,"enabled":true},{"fromId":286,"weight":-1.0955606,"enabled":true},{"fromId":49,"weight":0.0274162,"enabled":true},{"fromId":93,"weight":0.8503046,"enabled":true},{"fromId":13,"weight":-0.005052479,"enabled":true}]},{"id":52,"x":0.7,"incoming":[{"fromId":33,"weight":0.6924006,"enabled":true},{"fromId":0,"weight":0.60288024,"enabled":true},{"fromId":6,"weight":0.40615505,"enabled":true},{"fromId":65,"weight":2.681733,"enabled":true},{"fromId":9,"weight":-1.1942085,"enabled":true},{"fromId":102,"weight":0.72408307,"enabled":true},{"fromId":217,"weight":0.033540715,"enabled":true},{"fromId":303,"weight":1.5207566,"enabled":true}]},{"id":54,"x":0.7,"incoming":[{"fromId":31,"weight":0.5067991,"enabled":true},{"fromId":0,"weight":-0.9465078,"enabled":true},{"fromId":82,"weight":-0.26997706,"enabled":true},{"fromId":5,"weight":0.7570759,"enabled":true},{"fromId":26,"weight":0.690376,"enabled":true},{"fromId":25,"weight":0.29496697,"enabled":true},{"fromId":56,"weight":0.08123838,"enabled":true},{"fromId":85,"weight":1.1954995,"enabled":true},{"fromId":42,"weight":-0.8227163,"enabled":true},{"fromId":77,"weight":-0.33439717,"enabled":true},{"fromId":11,"weight":0.5281167,"enabled":true},{"fromId":231,"weight":-0.33063027,"enabled":true},{"fromId":49,"weight":0.6157229,"enabled":true},{"fromId":3,"weight":0.24388197,"enabled":true},{"fromId":14,"weight":-0.84543777,"enabled":true},{"fromId":70,"weight":1.5528055,"enabled":true}]},{"id":57,"x":0.7,"incoming":[{"fromId":0,"weight":-0.84119093,"enabled":true},{"fromId":5,"weight":-0.8239834,"enabled":true},{"fromId":1,"weight":-0.27463943,"enabled":true},{"fromId":88,"weight":-0.04794917,"enabled":true},{"fromId":29,"weight":0.008376688,"enabled":true},{"fromId":97,"weight":0.27308744,"enabled":true},{"fromId":123,"weight":-0.24953666,"enabled":true},{"fromId":282,"weight":-0.44768092,"enabled":true},{"fromId":2,"weight":-0.0051314235,"enabled":true},{"fromId":306,"weight":-0.045485735,"enabled":true},{"fromId":231,"weight":-0.23060071,"enabled":true},{"fromId":385,"weight":-0.21891925,"enabled":true},{"fromId":9,"weight":1.1444645,"enabled":true}]},{"id":59,"x":0.7,"incoming":[{"fromId":0,"weight":0.24495943,"enabled":true},{"fromId":22,"weight":-1.1308728,"enabled":true}]},{"id":60,"x":0.7,"incoming":[{"fromId":0,"weight":0.36287603,"enabled":true},{"fromId":37,"weight":1.973695,"enabled":true},{"fromId":56,"weight":-0.5144589,"enabled":true},{"fromId":64,"weight":0.3041429,"enabled":true},{"fromId":231,"weight":1.088251,"enabled":true},{"fromId":32,"weight":-0.3872587,"enabled":true}]},{"id":70,"x":0.7,"incoming":[{"fromId":41,"weight":-0.025024133,"enabled":true},{"fromId":0,"weight":-0.028582424,"enabled":true},{"fromId":37,"weight":-0.59371394,"enabled":true},{"fromId":82,"weight":-1.566334,"enabled":true},{"fromId":175,"weight":-0.709435,"enabled":true},{"fromId":235,"weight":0.51585305,"enabled":true},{"fromId":214,"weight":0.103027135,"enabled":true},{"fromId":11,"weight":-1.666033,"enabled":true},{"fromId":291,"weight":-0.10024142,"enabled":true},{"fromId":31,"weight":0.27269375,"enabled":true},{"fromId":285,"weight":0.50653076,"enabled":true}]},{"id":77,"x":0.7,"incoming":[{"fromId":31,"weight":1.4198273,"enabled":true},{"fromId":0,"weight":-0.74433506,"enabled":true},{"fromId":45,"weight":-0.67833227,"enabled":true},{"fromId":109,"weight":-1.7748667,"enabled":true},{"fromId":337,"weight":-0.16205475,"enabled":true},{"fromId":2,"weight":-0.41682297,"enabled":true}]},{"id":87,"x":0.7,"incoming":[{"fromId":40,"weight":1.4073448,"enabled":true},{"fromId":0,"weight":0.028559513,"enabled":true},{"fromId":266,"weight":-0.33342522,"enabled":true},{"fromId":7,"weight":-1.3820193,"enabled":true},{"fromId":265,"weight":0.22350621,"enabled":true},{"fromId":98,"weight":-0.9942931,"enabled":true}]},{"id":91,"x":0.7,"incoming":[{"fromId":6,"weight":0.37569427,"enabled":true},{"fromId":52,"weight":1.7614552,"enabled":true},{"fromId":0,"weight":0.8344282,"enabled":true},{"fromId":97,"weight":0.70039445,"enabled":true},{"fromId":362,"weight":-0.08295396,"enabled":true},{"fromId":365,"weight":-0.36722818,"enabled":true}]},{"id":119,"x":0.7,"incoming":[{"fromId":65,"weight":-1.2113665,"enabled":true},{"fromId":0,"weight":-0.44715697,"enabled":true},{"fromId":36,"weight":0.06966461,"enabled":true}]},{"id":141,"x":0.7,"incoming":[{"fromId":8,"weight":-0.4623209,"enabled":true},{"fromId":0,"weight":0.10516444,"enabled":true},{"fromId":167,"weight":-0.06275973,"enabled":true},{"fromId":178,"weight":-0.14360353,"enabled":true},{"fromId":379,"weight":1.1018937,"enabled":true}]},{"id":149,"x":0.7,"incoming":[{"fromId":56,"weight":0.38404533,"enabled":true},{"fromId":0,"weight":-0.25789887,"enabled":true},{"fromId":26,"weight":-1.7772626,"enabled":true},{"fromId":178,"weight":-0.5160349,"enabled":true},{"fromId":311,"weight":-0.20991862,"enabled":true}]},{"id":161,"x":0.7,"incoming":[{"fromId":45,"weight":2.135726,"enabled":true},{"fromId":0,"weight":-1.0857584,"enabled":true},{"fromId":25,"weight":0.032783456,"enabled":true},{"fromId":5,"weight":-0.68670666,"enabled":true},{"fromId":215,"weight":-0.39117083,"enabled":true},{"fromId":393,"weight":-0.5485233,"enabled":true},{"fromId":11,"weight":0.55134535,"enabled":true}]},{"id":198,"x":0.7,"incoming":[{"fromId":182,"weight":1.0783699,"enabled":true},{"fromId":0,"weight":-0.7009581,"enabled":true},{"fromId":45,"weight":-1.2079753,"enabled":true},{"fromId":365,"weight":-0.45265007,"enabled":true}]},{"id":205,"x":0.7,"incoming":[{"fromId":29,"weight":-0.042741146,"enabled":true},{"fromId":0,"weight":-0.43933317,"enabled":true},{"fromId":11,"weight":0.8451949,"enabled":true},{"fromId":3,"weight":0.34564242,"enabled":true},{"fromId":307,"weight":0.8001757,"enabled":true}]},{"id":217,"x":0.7,"incoming":[{"fromId":26,"weight":0.016670473,"enabled":true},{"fromId":0,"weight":0.4241435,"enabled":true},{"fromId":65,"weight":-1.1208013,"enabled":true},{"fromId":182,"weight":0.21581605,"enabled":true}]},{"id":284,"x":0.7,"incoming":[{"fromId":36,"weight":0.20304434,"enabled":true},{"fromId":0,"weight":0.22512308,"enabled":true},{"fromId":9,"weight":-0.11618353,"enabled":true},{"fromId":168,"weight":0.7721504,"enabled":true},{"fromId":145,"weight":1.5948493,"enabled":true},{"fromId":109,"weight":0.5985656,"enabled":true},{"fromId":4,"weight":-0.4089455,"enabled":true},{"fromId":68,"weight":0.8221153,"enabled":true},{"fromId":148,"weight":0.44230217,"enabled":true}]},{"id":310,"x":0.7,"incoming":[{"fromId":25,"weight":0.4682497,"enabled":true},{"fromId":0,"weight":-0.45449778,"enabled":true}]},{"id":378,"x":0.7,"incoming":[{"fromId":294,"weight":0.7099764,"enabled":true},{"fromId":0,"weight":-0.526659,"enabled":true}]},{"id":397,"x":0.7,"incoming":[{"fromId":35,"weight":-0.6671313,"enabled":true},{"fromId":0,"weight":-0.5507706,"enabled":true}]},{"id":213,"x":0.75,"incoming":[{"fromId":107,"weight":-0.22351372,"enabled":true},{"fromId":0,"weight":-0.23855072,"enabled":true},{"fromId":102,"weight":0.8812562,"enabled":true},{"fromId":85,"weight":1.334346,"enabled":true},{"fromId":510,"weight":1.1813164,"enabled":true}]},{"id":53,"x":0.79999995,"incoming":[{"fromId":31,"weight":0.21986476,"enabled":true},{"fromId":0,"weight":-0.89758325,"enabled":true},{"fromId":164,"weight":0.8208052,"enabled":true},{"fromId":3,"weight":2.0751193,"enabled":true},{"fromId":4,"weight":-0.02689398,"enabled":true},{"fromId":37,"weight":-0.81483865,"enabled":true},{"fromId":93,"weight":-0.71379787,"enabled":true},{"fromId":380,"weight":0.24668917,"enabled":true},{"fromId":204,"weight":0.24391918,"enabled":true},{"fromId":133,"weight":-0.671957,"enabled":true}]},{"id":63,"x":0.79999995,"incoming":[{"fromId":54,"weight":0.0076157097,"enabled":true},{"fromId":0,"weight":0.6000557,"enabled":true},{"fromId":88,"weight":-0.5905664,"enabled":true},{"fromId":256,"weight":0.3822567,"enabled":true},{"fromId":3,"weight":-0.23998709,"enabled":true},{"fromId":27,"weight":0.68709683,"enabled":true},{"fromId":94,"weight":-0.7317267,"enabled":true},{"fromId":249,"weight":-0.78715384,"enabled":true}]},{"id":105,"x":0.79999995,"incoming":[{"fromId":31,"weight":-0.30549493,"enabled":true},{"fromId":0,"weight":0.973487,"enabled":true},{"fromId":51,"weight":-0.017529756,"enabled":true},{"fromId":94,"weight":-0.07186697,"enabled":true},{"fromId":58,"weight":-1.4323605,"enabled":true},{"fromId":6,"weight":-0.48637798,"enabled":true}]},{"id":212,"x":0.79999995,"incoming":[{"fromId":121,"weight":-0.7407186,"enabled":true},{"fromId":0,"weight":0.40013513,"enabled":true},{"fromId":171,"weight":-1.7162228,"enabled":true},{"fromId":88,"weight":-0.15369973,"enabled":true}]},{"id":239,"x":0.79999995,"incoming":[{"fromId":149,"weight":0.79285264,"enabled":true},{"fromId":0,"weight":-1.019078,"enabled":true},{"fromId":51,"weight":0.090800695,"enabled":true},{"fromId":1,"weight":0.15904438,"enabled":true},{"fromId":8,"weight":-1.5081494,"enabled":true},{"fromId":389,"weight":-0.08787696,"enabled":true}]},{"id":358,"x":0.79999995,"incoming":[{"fromId":52,"weight":-0.20605674,"enabled":true},{"fromId":0,"weight":-1.1282965,"enabled":true}]},{"id":367,"x":0.79999995,"incoming":[{"fromId":161,"weight":-1.2003157,"enabled":true},{"fromId":0,"weight":-0.3576179,"enabled":true},{"fromId":377,"weight":-1.2235892,"enabled":true},{"fromId":14,"weight":-0.16026866,"enabled":true},{"fromId":222,"weight":-0.44844988,"enabled":true}]},{"id":308,"x":0.84999996,"incoming":[{"fromId":53,"weight":-0.4468778,"enabled":true},{"fromId":0,"weight":-0.43961746,"enabled":true},{"fromId":167,"weight":1.096484,"enabled":true},{"fromId":408,"weight":-0.3796791,"enabled":true}]},{"id":71,"x":0.9,"incoming":[{"fromId":25,"weight":-0.44509685,"enabled":true},{"fromId":0,"weight":-0.3071779,"enabled":true},{"fromId":150,"weight":-1.5594528,"enabled":true},{"fromId":49,"weight":0.32040507,"enabled":true},{"fromId":69,"weight":-0.5572188,"enabled":true},{"fromId":310,"weight":-0.0063667,"enabled":true},{"fromId":370,"weight":0.94956726,"enabled":true}]},{"id":95,"x":0.9,"incoming":[{"fromId":21,"weight":0.2428853,"enabled":true},{"fromId":0,"weight":-0.8586436,"enabled":true},{"fromId":8,"weight":-0.27002838,"enabled":true},{"fromId":29,"weight":-0.6454337,"enabled":true},{"fromId":25,"weight":0.15208034,"enabled":true},{"fromId":38,"weight":3.1588182,"enabled":true},{"fromId":36,"weight":-0.7958205,"enabled":true},{"fromId":161,"weight":0.034242086,"enabled":true},{"fromId":4,"weight":0.8516609,"enabled":true},{"fromId":133,"weight":-0.11778358,"enabled":true},{"fromId":11,"weight":0.5672154,"enabled":true},{"fromId":378,"weight":-0.7731564,"enabled":true},{"fromId":294,"weight":-0.102416605,"enabled":true},{"fromId":26,"weight":0.79917717,"enabled":true},{"fromId":286,"weight":-1.195612,"enabled":true},{"fromId":556,"weight":-0.75496936,"enabled":true}]},{"id":110,"x":0.9,"incoming":[{"fromId":21,"weight":-0.6551015,"enabled":true},{"fromId":0,"weight":-0.075667985,"enabled":true},{"fromId":1,"weight":-0.245071,"enabled":true},{"fromId":29,"weight":1.90279,"enabled":true},{"fromId":69,"weight":-1.186809,"enabled":true},{"fromId":88,"weight":-0.1579801,"enabled":true},{"fromId":7,"weight":-0.6609237,"enabled":true},{"fromId":64,"weight":-0.21457739,"enabled":true},{"fromId":205,"weight":-1.5241928,"enabled":true},{"fromId":45,"weight":1.0963085,"enabled":true},{"fromId":182,"weight":1.2483169,"enabled":true},{"fromId":32,"weight":0.032358825,"enabled":true},{"fromId":331,"weight":-0.94900227,"enabled":true},{"fromId":3,"weight":-0.027974278,"enabled":true}]},{"id":112,"x":0.9,"incoming":[{"fromId":0,"weight":1.0973341,"enabled":true},{"fromId":11,"weight":1.4838284,"enabled":true},{"fromId":89,"weight":-1.4526125,"enabled":true},{"fromId":138,"weight":-1.3689905,"enabled":true},{"fromId":14,"weight":-1.6329343,"enabled":true},{"fromId":91,"weight":-0.39964592,"enabled":false},{"fromId":448,"weight":-0.14328265,"enabled":true},{"fromId":65,"weight":1.6356599,"enabled":true}]},{"id":137,"x":0.9,"incoming":[{"fromId":49,"weight":-0.6642718,"enabled":true},{"fromId":0,"weight":0.13155895,"enabled":true},{"fromId":46,"weight":-0.4022744,"enabled":true},{"fromId":53,"weight":0.08752979,"enabled":true},{"fromId":4,"weight":-0.43487957,"enabled":true},{"fromId":63,"weight":0.90441257,"enabled":true},{"fromId":8,"weight":-0.67853135,"enabled":true},{"fromId":308,"weight":-0.19254547,"enabled":true},{"fromId":239,"weight":-1.2449559,"enabled":true},{"fromId":302,"weight":0.005388066,"enabled":true}]},{"id":151,"x":0.9,"incoming":[{"fromId":0,"weight":0.019674607,"enabled":true},{"fromId":37,"weight":0.3092286,"enabled":true},{"fromId":87,"weight":0.47795996,"enabled":true}]},{"id":307,"x":0.9,"incoming":[{"fromId":0,"weight":0.29257447,"enabled":true},{"fromId":29,"weight":0.49203518,"enabled":true}]}],"outputs":[{"id":21,"x":0.9,"incoming":[{"fromId":0,"weight":-1.1476038,"enabled":true},{"fromId":1,"weight":2.5936177,"enabled":true},{"fromId":2,"weight":-0.2607125,"enabled":true},{"fromId":3,"weight":0.81244105,"enabled":true},{"fromId":4,"weight":0.6872877,"enabled":true},{"fromId":25,"weight":1.0016313,"enabled":true},{"fromId":31,"weight":0.8371141,"enabled":true},{"fromId":22,"weight":-0.53085643,"enabled":true},{"fromId":54,"weight":2.0391262,"enabled":true},{"fromId":21,"weight":0.8739069,"enabled":true},{"fromId":42,"weight":1.1101421,"enabled":true},{"fromId":63,"weight":-0.819733,"enabled":true},{"fromId":39,"weight":-1.1712718,"enabled":true},{"fromId":6,"weight":0.5396671,"enabled":true},{"fromId":95,"weight":0.2708849,"enabled":true},{"fromId":53,"weight":-0.90169895,"enabled":true},{"fromId":51,"weight":0.74822724,"enabled":true},{"fromId":94,"weight":0.62010294,"enabled":true},{"fromId":7,"weight":0.3422392,"enabled":true},{"fromId":52,"weight":-0.45424107,"enabled":true},{"fromId":227,"weight":-0.09661564,"enabled":true},{"fromId":202,"weight":-0.533366,"enabled":true},{"fromId":358,"weight":1.5715752,"enabled":true},{"fromId":360,"weight":-0.49129465,"enabled":true},{"fromId":59,"weight":-0.56703,"enabled":true}]},{"id":22,"x":0.9,"incoming":[{"fromId":0,"weight":0.4459573,"enabled":true},{"fromId":1,"weight":-1.0634882,"enabled":true},{"fromId":2,"weight":1.4955934,"enabled":true},{"fromId":3,"weight":0.23775089,"enabled":true},{"fromId":4,"weight":-0.88905245,"enabled":true},{"fromId":40,"weight":-0.43386695,"enabled":true},{"fromId":25,"weight":1.5791715,"enabled":true},{"fromId":42,"weight":0.84997565,"enabled":true},{"fromId":49,"weight":-0.52467597,"enabled":true},{"fromId":38,"weight":-0.66046554,"enabled":true},{"fromId":41,"weight":0.8303231,"enabled":true},{"fromId":37,"weight":1.0511198,"enabled":true},{"fromId":5,"weight":0.26356834,"enabled":true},{"fromId":7,"weight":-0.6247289,"enabled":true},{"fromId":45,"weight":1.1153021,"enabled":true},{"fromId":70,"weight":0.14849561,"enabled":true},{"fromId":56,"weight":-0.62384313,"enabled":true},{"fromId":26,"weight":-1.6483347,"enabled":true},{"fromId":22,"weight":0.41383237,"enabled":true},{"fromId":149,"weight":-0.7541568,"enabled":true},{"fromId":161,"weight":0.587048,"enabled":true},{"fromId":93,"weight":-0.86401594,"enabled":true},{"fromId":11,"weight":-0.84467226,"enabled":true},{"fromId":33,"weight":-0.3574038,"enabled":true},{"fromId":182,"weight":-0.13874575,"enabled":true},{"fromId":198,"weight":1.139787,"enabled":true},{"fromId":36,"weight":-0.57347625,"enabled":true},{"fromId":239,"weight":0.023431234,"enabled":true},{"fromId":284,"weight":-0.27231547,"enabled":true},{"fromId":238,"weight":-0.79830694,"enabled":true},{"fromId":30,"weight":0.49230054,"enabled":true},{"fromId":47,"weight":-1.1202406,"enabled":true},{"fromId":51,"weight":1.3176345,"enabled":true},{"fromId":317,"weight":1.6272244,"enabled":true},{"fromId":14,"weight":-0.2792162,"enabled":true},{"fromId":35,"weight":0.50141126,"enabled":true},{"fromId":367,"weight":0.0057760775,"enabled":true},{"fromId":397,"weight":-0.8874939,"enabled":true},{"fromId":151,"weight":-0.9082802,"enabled":true}]},{"id":23,"x":0.9,"incoming":[{"fromId":0,"weight":0.84681535,"enabled":true},{"fromId":1,"weight":1.1303474,"enabled":true},{"fromId":2,"weight":-1.0535879,"enabled":true},{"fromId":3,"weight":1.1830764,"enabled":true},{"fromId":4,"weight":1.38372,"enabled":true},{"fromId":37,"weight":-0.046718977,"enabled":true},{"fromId":32,"weight":-0.32829165,"enabled":true},{"fromId":42,"weight":-1.756573,"enabled":true},{"fromId":33,"weight":-0.6633422,"enabled":true},{"fromId":7,"weight":1.2845511,"enabled":true},{"fromId":29,"weight":0.73103607,"enabled":true},{"fromId":49,"weight":2.9884415,"enabled":true},{"fromId":27,"weight":-0.12325634,"enabled":true},{"fromId":60,"weight":0.58668965,"enabled":true},{"fromId":114,"weight":-0.04639788,"enabled":true},{"fromId":97,"weight":-1.1626927,"enabled":true},{"fromId":6,"weight":-1.8909984,"enabled":true},{"fromId":137,"weight":-0.0074397027,"enabled":true},{"fromId":26,"weight":-0.24347708,"enabled":true},{"fromId":13,"weight":1.2631116,"enabled":true},{"fromId":110,"weight":0.25526547,"enabled":true},{"fromId":217,"weight":-0.41003463,"enabled":true},{"fromId":98,"weight":-0.93236613,"enabled":true},{"fromId":175,"weight":-0.617719,"enabled":true},{"fromId":239,"weight":-0.8416704,"enabled":true},{"fromId":305,"weight":-0.12906416,"enabled":true},{"fromId":89,"weight":0.69936067,"enabled":true},{"fromId":152,"weight":-0.19835933,"enabled":true}]},{"id":24,"x":0.9,"incoming":[{"fromId":0,"weight":-0.3327304,"enabled":true},{"fromId":1,"weight":-0.047340624,"enabled":true},{"fromId":2,"weight":-0.93745625,"enabled":true},{"fromId":3,"weight":0.26174086,"enabled":true},{"fromId":4,"weight":1.4134964,"enabled":false},{"fromId":25,"weight":-0.271341,"enabled":true},{"fromId":29,"weight":0.057147507,"enabled":true},{"fromId":33,"weight":1.1570245,"enabled":true},{"fromId":40,"weight":0.8163044,"enabled":true},{"fromId":51,"weight":0.13713884,"enabled":true},{"fromId":6,"weight":-1.8559312,"enabled":true},{"fromId":52,"weight":-0.20974007,"enabled":true},{"fromId":26,"weight":-0.18067576,"enabled":true},{"fromId":7,"weight":-0.65061015,"enabled":true},{"fromId":31,"weight":1.05512,"enabled":true},{"fromId":88,"weight":0.017509043,"enabled":true},{"fromId":82,"weight":-0.8554237,"enabled":true},{"fromId":107,"weight":-1.1029681,"enabled":true},{"fromId":114,"weight":-0.11284238,"enabled":true},{"fromId":32,"weight":-1.5953379,"enabled":true},{"fromId":87,"weight":0.20929924,"enabled":true},{"fromId":46,"weight":0.077598184,"enabled":true},{"fromId":194,"weight":-0.20881641,"enabled":true},{"fromId":41,"weight":-0.76929677,"enabled":true},{"fromId":71,"weight":-0.82602394,"enabled":true},{"fromId":21,"weight":0.4927054,"enabled":true},{"fromId":136,"weight":-0.4463724,"enabled":true},{"fromId":213,"weight":-0.80935097,"enabled":true},{"fromId":91,"weight":-1.633551,"enabled":true},{"fromId":337,"weight":-0.49875543,"enabled":true},{"fromId":351,"weight":0.39066318,"enabled":true}]}]}